mets/__init__.py
mets/mets.py
mets-0.1.3.dist-info/LICENSE
mets-0.1.3.dist-info/METADATA
mets-0.1.3.dist-info/WHEEL
mets-0.1.3.dist-info/entry_points.txt
mets-0.1.3.dist-info/top_level.txt
mets-0.1.3.dist-info/RECORD
