Metadata-Version: 2.1
Name: mets
Version: 0.1.3
Summary: A CLI tool for searching and retrieving data from the Metropolitan Museum of Art API
Author-email: Alex Khalyavin <soluwell3@gmail.com>
License: MIT
Project-URL: Homepage, https://gitlab.com/cgs2824870/mets
Project-URL: Repository, https://gitlab.com/cgs2824870/mets.git
Classifier: Development Status :: 3 - Alpha
Classifier: Intended Audience :: Developers
Classifier: License :: OSI Approved :: MIT License
Classifier: Operating System :: OS Independent
Classifier: Programming Language :: Python :: 3
Classifier: Programming Language :: Python :: 3.10
Classifier: Programming Language :: Python :: 3.11
Classifier: Programming Language :: Python :: 3.12
Requires-Python: >=3.10
License-File: LICENSE
Requires-Dist: aiofiles
Requires-Dist: httpx
Requires-Dist: tqdm
Provides-Extra: test
Requires-Dist: pytest ; extra == 'test'
Requires-Dist: pytest-cov ; extra == 'test'
